getrails/__init__.py
getrails/duckduckgo/search.py
getrails/google/search.py
getrails/vidalia/search.py
getrails-3.3.dist-info/LICENSE
getrails-3.3.dist-info/METADATA
getrails-3.3.dist-info/WHEEL
getrails-3.3.dist-info/top_level.txt
getrails-3.3.dist-info/RECORD
