Metadata-Version: 2.1
Name: getrails
Version: 3.3
Summary: Tool of OSINT and Dork hacking that work with Google, Duckduckgo and Onion likes
Home-page: https://github.com/Jul10l1r4/getrails
Author: Julio Lira
Author-email: jul10l1r4@disroot.org
License: GPLv3
Keywords: getrails get trails google duckduckgo tor onion torch vidalia osint
Platform: UNKNOWN
Classifier: Programming Language :: Python :: 3
Classifier: License :: OSI Approved :: GNU General Public License v3 or later (GPLv3+)
Classifier: Operating System :: OS Independent
Classifier: Topic :: Security
Classifier: Topic :: Internet :: WWW/HTTP :: Indexing/Search
License-File: LICENSE
Requires-Dist: mechanicalsoup
Requires-Dist: google
